animepy/__init__.py
animepy/anigamer.py
animepy/main_test.py
animepy/response/__init__.py
animepy/response/anigamer.py
animepy/response/anisearch.py
animepy/response/errors.py
newanimepy-0.0.2.dist-info/LICENSE
newanimepy-0.0.2.dist-info/METADATA
newanimepy-0.0.2.dist-info/WHEEL
newanimepy-0.0.2.dist-info/top_level.txt
newanimepy-0.0.2.dist-info/RECORD
