Metadata-Version: 2.1
Name: newanimepy
Version: 0.0.2
Summary: An anime crawler
Home-page: https://github.com/z20030818/NewAnimepy
Author: Misaka0502
Author-email: remisaka0502@gmail.com
Classifier: Programming Language :: Python :: 3.9
License-File: LICENSE
Requires-Dist: requests
Requires-Dist: bs4
